taiz-0.1.dist-info/licenses/LICENSE.txt
taizun/__init__.py
taizun/nlp.py
taizun/utils.py
taizun/vision.py
taiz-0.1.dist-info/METADATA
taiz-0.1.dist-info/WHEEL
taiz-0.1.dist-info/top_level.txt
taiz-0.1.dist-info/RECORD
