Metadata-Version: 2.4
Name: taiz
Version: 0.1
Summary: A Python library for simplifying tasks and enhancing generative AI workflows.
Home-page: https://github.com/t4zn/taizun
Author: Taizun
Author-email: taizun8@gmail.com
Classifier: Programming Language :: Python :: 3
Classifier: License :: OSI Approved :: MIT License
Classifier: Operating System :: OS Independent
Requires-Python: >=3.6
License-File: LICENSE.txt
Requires-Dist: transformers
Requires-Dist: torch
Requires-Dist: Pillow
Dynamic: author
Dynamic: author-email
Dynamic: classifier
Dynamic: description
Dynamic: description-content-type
Dynamic: home-page
Dynamic: license-file
Dynamic: requires-dist
Dynamic: requires-python
Dynamic: summary
